Workbook

Sheet 1_Ist_Daten
A1: Feld | B1: Wert | C1: Einheit | D1: Hinweis (Aus letzter Excel)
A2: Kassenbestand (Start Periode) | B2: 28.05 | C2: MEUR | D2: Aus Bilanz Aktiva
A3: Eigenkapital | B3: 35.25 | C3: MEUR | D3: Aus Bilanz Passiva
A4: Gewinnvortrag | B4: 5.27 | C4: MEUR | D4: Maximal mögliche Dividende
A5: Pensionsrückstellungen | B5: 15.95 | C5: MEUR | D5: Passiva
A6: Geplante E-Steuer (%) | B6: 0.3 | C6: % | D6: Im Handbuch prüfen. 0.30 = 30%
A7: Zinssatz Langfristig (%) | B7: 0.06 | C7: % | D7: Bsp: 6% aus Berichten
A8: Zinssatz Kurzfristig (%) | B8: 0.08 | C8: % | D8: Bsp: 8% aus Berichten

Sheet 2_Team_Inputs
A1: Feld | B1: Wert | C1: Einheit | D1: Hinweis (Vom Team erfragen)
A2: Geplante Absatzmenge | B2: 45000 | C2: Stück | D2: Planzahl Vertrieb
A3: Geplanter Preis | B3: 3000 | C3: EUR | D3: Planzahl Vertrieb
A4: --- KERNAUSGABEN ---
A5: Total Herstellkosten | B5: 90 | C5: MEUR | D5: inkl. Personal in Fertigung
A6: Total Verwaltungskosten | B6: 10 | C6: MEUR
A7: Total Marketing/Vertrieb | B7: 15 | C7: MEUR
A8: --- INVESTITIONEN ---
A9: Abschreibungen Alt-Anlagen | B9: 6 | C9: MEUR | D9: GuV / Anlagenblatt
A10: Geplante Neuinvestition (Maschine) | B10: 15 | C10: MEUR | D10: Totaler Kaufpreis - Cash Out!
A11: Geplante Neu-Abschreibung | B11: 1.5 | C11: MEUR | D11: Z.B. 10% von Maschine
A12: Veränderung Pensionsrückstellungen | B12: 2 | C12: MEUR | D12: Positiv = Cash-plus

Sheet 3_Szenario_Rechner
A1: Feld | B1: Szenario A (Defensiv) | C1: Szenario B (Aggressiv) | D1: Szenario C
A2: --- 1: EINGABEN (DEINE CFO ENTSCHEIDUNG) ---
A3: Kurzfristiger Kredit (MEUR) | B3: 0 | C3: 15 | D3: 5
A4: Langfristiger Kredit (MEUR) | B4: 0 | C4: 20 | D4: 10
A5: Dividende (MEUR) | B5: 40 | C5: 0 | D5: 2
A6: Geplanter Wertpapierkauf | B6: 0 | C6: 0 | D6: 0
A7: --- 2: BERECHNUNG EBIT & GEWINN ---
A8: Plan-Umsatz | B8: ='2_Team_Inputs'!B2*'2_Team_Inputs'!B3/1000000 -> 135 | C8: ='2_Team_Inputs'!B2*'2_Team_Inputs'!B3/1000000 -> 135 | D8: ='2_Team_Inputs'!B2*'2_Team_Inputs'!B3/1000000 -> 135
A9: Plan-EBIT | B9: =B8-'2_Team_Inputs'!B5-'2_Team_Inputs'!B6-'2_Team_Inputs'!B7-'2_Team_Inputs'!B9-'2_Team_Inputs'!B11 -> 12.5 | C9: =C8-'2_Team_Inputs'!B5-'2_Team_Inputs'!B6-'2_Team_Inputs'!B7-'2_Team_Inputs'!B9-'2_Team_Inputs'!B11 -> 12.5 | D9: =D8-'2_Team_Inputs'!B5-'2_Team_Inputs'!B6-'2_Team_Inputs'!B7-'2_Team_Inputs'!B9-'2_Team_Inputs'!B11 -> 12.5
A10: Plan-Zinsaufwand | B10: =(B3*'1_Ist_Daten'!B8)+(B4*'1_Ist_Daten'!B7) -> 0 | C10: =(C3*'1_Ist_Daten'!B8)+(C4*'1_Ist_Daten'!B7) -> 2.4 | D10: =(D3*'1_Ist_Daten'!B8)+(D4*'1_Ist_Daten'!B7) -> 1
A11: Plan-EBT (Ergebnis vor Steuern) | B11: =B9-B10 -> 12.5 | C11: =C9-C10 -> 10.1 | D11: =D9-D10 -> 11.5
A12: Plan-Steuern | B12: =IF(B11>0, B11*'1_Ist_Daten'!B6, 0) -> 3.75 | C12: =IF(C11>0, C11*'1_Ist_Daten'!B6, 0) -> 3.03 | D12: =IF(D11>0, D11*'1_Ist_Daten'!B6, 0) -> 3.45
A13: Plan-Jahresüberschuss | B13: =B11-B12 -> 8.75 | C13: =C11-C12 -> 7.07 | D13: =D11-D12 -> 8.05
A14: --- 3: TOPSIM ZIELEINGABEN ---
A15: Plan-Eigenkapital | B15: ='1_Ist_Daten'!B3+B13-B5 -> 4 | C15: ='1_Ist_Daten'!B3+C13-C5 -> 42.32 | D15: ='1_Ist_Daten'!B3+D13-D5 -> 41.3
A16: Plan-EKR (%) | B16: =(B13/B15)*100 -> 218.75 | C16: =(C13/C15)*100 -> 16.706049 | D16: =(D13/D15)*100 -> 19.491525
A17: Plan-Operativer Cashflow (MEUR) | B17: =B13+'2_Team_Inputs'!B9+'2_Team_Inputs'!B11+'2_Team_Inputs'!B12 -> 18.25 | C17: =C13+'2_Team_Inputs'!B9+'2_Team_Inputs'!B11+'2_Team_Inputs'!B12 -> 16.57 | D17: =D13+'2_Team_Inputs'!B9+'2_Team_Inputs'!B11+'2_Team_Inputs'!B12 -> 17.55
A18: --- 4: TOPSIM FATAL CHECK ---
A19: Kassenbestand ENDE (Darf NIEMALS < 0 sein!) | B19: ='1_Ist_Daten'!B2+B17+B3+B4-B5-'2_Team_Inputs'!B10-B6 -> -8.7 | C19: ='1_Ist_Daten'!B2+C17+C3+C4-C5-'2_Team_Inputs'!B10-C6 -> 64.62 | D19: ='1_Ist_Daten'!B2+D17+D3+D4-D5-'2_Team_Inputs'!B10-D6 -> 43.6
