Workbook

Sheet 1_Ist_Daten
A1: Feld | B1: Wert | C1: Einheit | D1: Hinweis (Aus letzter Excel/Berichten)
A2: Kassenbestand (Start Periode) | B2: 28.05 | C2: MEUR | D2: Aus Bilanz Aktiva
A3: Eigenkapital | B3: 35.25 | C3: MEUR | D3: Aus Bilanz Passiva
A4: Gewinnvortrag | B4: 5.27 | C4: MEUR | D4: Maximal mögliche Dividende
A5: Steuerlicher Verlustvortrag | B5: 0 | C5: MEUR | D5: Vorjahresverlust (vermindert Steuern)
A6: Pensionsrückstellungen | B6: 15.95 | C6: MEUR | D6: Passiva
A7: Bestehende Kurzfristkredite (Alt) | B7: 12 | C7: MEUR | D7: Werden auto-getilgt (fließen zwingend ab!)
A8: Bestehende Langfristkredite (Alt) | B8: 20 | C8: MEUR | D8: Nur für Plan-Zinsen wichtig
A9: Geplante E-Steuer (%) | B9: 0.45 | C9: % | D9: Im Handbuch S.33 klar auf 45% festgelegt
A10: Zinssatz Langfristig (%) | B10: 0.07 | C10: % | D10: Bsp: 7% aus Handbuch S.31 / Per.0
A11: Zinssatz Kurzfristig (%) | B11: 0.08 | C11: % | D11: Bsp: 8% aus Berichten / Per.0
A12: Zinssatz Überziehen (%) | B12: 0.13 | C12: % | D12: 13% Strafzins (Handbuch)

Sheet 2_Team_Inputs
A1: Feld | B1: Wert | C1: Einheit | D1: Hinweis (Vom Team erfragen)
A2: Geplante Absatzmenge | B2: 45000 | C2: Stück | D2: Planzahl Vertrieb
A3: Geplanter Preis | B3: 3000 | C3: EUR | D3: Planzahl Vertrieb
A4: --- KERNAUSGABEN ---
A5: Total Herstellkosten | B5: 90 | C5: MEUR | D5: inkl. Personal in Fertigung
A6: Total Verwaltungskosten | B6: 10 | C6: MEUR
A7: Total Marketing/Vertrieb | B7: 15 | C7: MEUR
A8: Forschung & Entwicklung (F&E) | B8: 2.5 | C8: MEUR | D8: Ökologie, Technologie, etc.
A9: Marktforschung | B9: 0.15 | C9: MEUR | D9: Kosten für Berichte / Analysen
A10: --- INVESTITIONEN ---
A11: Freiwillige Tilgung Langfristkr. | B11: 0 | C11: MEUR | D11: HIER NICHTS EINTRAGEN
A12: Abschreibungen Alt-Anlagen | B12: 6 | C12: MEUR | D12: inklusive 0.25 MEUR fixe Gebäude-AfA
A13: Geplante Neuinvestition | B13: 15 | C13: MEUR | D13: Totaler Kaufpreis Anlage - Cash Out!
A14: Geplante Neu-Abschreibung | B14: 1.5 | C14: MEUR | D14: Z.B. 10% Lineare Abschreibung
A15: Veränderung Pensionsrückstellungen | B15: 2 | C15: MEUR | D15: Positiv = Cash-plus
A16: Geplante Produktionsmenge | B16: 45000 | C16: Stück | D16: Für Bestandsveränderung (Fertigung)

Sheet 3_Szenario_Rechner
A1: Feld | B1: Szenario A (Defensiv) | C1: Szenario B (Aggressiv) | D1: Szenario C
A2: --- 1: EINGABEN (DEINE CFO ENTSCHEIDUNG) ---
A3: NEUER Kurzfristiger Kredit (MEUR) | B3: 15 | C3: 20 | D3: 10
A4: NEUER Langfristiger Kredit (MEUR) | B4: 0 | C4: 10 | D4: 0
A5: Dividende (MEUR) | B5: 1 | C5: 0 | D5: 2
A6: Geplanter Wertpapierkauf | B6: 0 | C6: 0 | D6: 0
A7: --- 2: BERECHNUNG EBIT & GEWINN ---
A8: Plan-Umsatz | B8: ='2_Team_Inputs'!B2*'2_Team_Inputs'!B3/1000000 -> 135 | C8: ='2_Team_Inputs'!B2*'2_Team_Inputs'!B3/1000000 -> 135 | D8: ='2_Team_Inputs'!B2*'2_Team_Inputs'!B3/1000000 -> 135
A9: Plan-Bestandsveränderung | B9: =IF('2_Team_Inputs'!B16>0, ('2_Team_Inputs'!B16-'2_Team_Inputs'!B2)*('2_Team_Inputs'!B5/'2_Team_Inputs'!B16), 0) -> 0 | C9: =IF('2_Team_Inputs'!B16>0, ('2_Team_Inputs'!B16-'2_Team_Inputs'!B2)*('2_Team_Inputs'!B5/'2_Team_Inputs'!B16), 0) -> 0 | D9: =IF('2_Team_Inputs'!B16>0, ('2_Team_Inputs'!B16-'2_Team_Inputs'!B2)*('2_Team_Inputs'!B5/'2_Team_Inputs'!B16), 0) -> 0
A10: Plan-EBIT | B10: =B8+B9-SUM('2_Team_Inputs'!B5:B9)-'2_Team_Inputs'!B12-'2_Team_Inputs'!B14 -> 9.85 | C10: =C8+C9-SUM('2_Team_Inputs'!B5:B9)-'2_Team_Inputs'!B12-'2_Team_Inputs'!B14 -> 9.85 | D10: =D8+D9-SUM('2_Team_Inputs'!B5:B9)-'2_Team_Inputs'!B12-'2_Team_Inputs'!B14 -> 9.85
A11: Plan-Zinsaufwand | B11: =((B3+'1_Ist_Daten'!B7)*'1_Ist_Daten'!B11)+((B4+'1_Ist_Daten'!B8-'2_Team_Inputs'!B11)*'1_Ist_Daten'!B10) -> 3.56 | C11: =((C3+'1_Ist_Daten'!B7)*'1_Ist_Daten'!B11)+((C4+'1_Ist_Daten'!B8-'2_Team_Inputs'!B11)*'1_Ist_Daten'!B10) -> 4.66 | D11: =((D3+'1_Ist_Daten'!B7)*'1_Ist_Daten'!B11)+((D4+'1_Ist_Daten'!B8-'2_Team_Inputs'!B11)*'1_Ist_Daten'!B10) -> 3.16
A12: Plan-EBT (Ergebnis vor Steuern) | B12: =B10-B11 -> 6.29 | C12: =C10-C11 -> 5.19 | D12: =D10-D11 -> 6.69
A13: Bemessungsgrundlage Steuer | B13: =MAX(0, B12-'1_Ist_Daten'!B5) -> 6.29 | C13: =MAX(0, C12-'1_Ist_Daten'!B5) -> 5.19 | D13: =MAX(0, D12-'1_Ist_Daten'!B5) -> 6.69
A14: Plan-Steuern | B14: =B13*'1_Ist_Daten'!B9 -> 2.8305 | C14: =C13*'1_Ist_Daten'!B9 -> 2.3355 | D14: =D13*'1_Ist_Daten'!B9 -> 3.0105
A15: Plan-Jahresüberschuss | B15: =B12-B14 -> 3.4595 | C15: =C12-C14 -> 2.8545 | D15: =D12-D14 -> 3.6795
A16: --- 3: TOPSIM ZIELEINGABEN ---
A17: Plan-Eigenkapital | B17: ='1_Ist_Daten'!B3+B15-B5 -> 37.7095 | C17: ='1_Ist_Daten'!B3+C15-C5 -> 38.1045 | D17: ='1_Ist_Daten'!B3+D15-D5 -> 36.9295
A18: Plan-EKR (%) | B18: =(B15/B17)*100 -> 9.1740808 | C18: =(C15/C17)*100 -> 7.4912412 | D18: =(D15/D17)*100 -> 9.9635793
A19: Plan-Operativer Cashflow (MEUR) | B19: =B15+'2_Team_Inputs'!B12+'2_Team_Inputs'!B14+'2_Team_Inputs'!B15 -> 12.9595 | C19: =C15+'2_Team_Inputs'!B12+'2_Team_Inputs'!B14+'2_Team_Inputs'!B15 -> 12.3545 | D19: =D15+'2_Team_Inputs'!B12+'2_Team_Inputs'!B14+'2_Team_Inputs'!B15 -> 13.1795
A20: --- 4: TOPSIM FATAL CHECK ---
A21: Kassenbestand ENDE (Alarm < 0) | B21: ='1_Ist_Daten'!B2+B19+B3+B4-B5-'2_Team_Inputs'!B13-'1_Ist_Daten'!B7-'2_Team_Inputs'!B11-B6 -> 28.0095 | C21: ='1_Ist_Daten'!B2+C19+C3+C4-C5-'2_Team_Inputs'!B13-'1_Ist_Daten'!B7-'2_Team_Inputs'!B11-C6 -> 43.4045 | D21: ='1_Ist_Daten'!B2+D19+D3+D4-D5-'2_Team_Inputs'!B13-'1_Ist_Daten'!B7-'2_Team_Inputs'!B11-D6 -> 22.2295
