Workbook

Sheet 1_Ist_Daten
A1: Feld | B1: Wert | C1: Einheit | D1: Hinweis (Aus letzter Excel/Berichten)
A2: Kassenbestand (Start Periode) | B2: 28.05 | C2: MEUR | D2: Aus Bilanz Aktiva
A3: Eigenkapital | B3: 35.25 | C3: MEUR | D3: Aus Bilanz Passiva
A4: Gewinnvortrag | B4: 5.27 | C4: MEUR | D4: Maximal mögliche Dividende
A5: Steuerlicher Verlustvortrag | B5: 0 | C5: MEUR | D5: Vorjahresverlust (vermindert Steuern)
A6: Pensionsrückstellungen | B6: 15.95 | C6: MEUR | D6: Passiva
A7: Bestehende Kurzfristkredite (Alt) | B7: 12 | C7: MEUR | D7: Werden auto-getilgt (fließen zwingend ab!)
A8: Bestehende Langfristkredite (Alt) | B8: 20 | C8: MEUR | D8: Nur für Plan-Zinsen wichtig
A9: Geplante E-Steuer (%) | B9: 0.45 | C9: % | D9: Im Handbuch S.33 klar auf 45% festgelegt
A10: Zinssatz Langfristig (%) | B10: 0.07 | C10: % | D10: Bsp: 7% aus Handbuch S.31 / Per.0
A11: Zinssatz Kurzfristig (%) | B11: 0.08 | C11: % | D11: Bsp: 8% aus Berichten / Per.0
A12: Zinssatz Überziehen (%) | B12: 0.13 | C12: % | D12: 13% Strafzins (Handbuch)

Sheet 2_Team_Inputs
A1: Feld | B1: Wert | C1: Einheit | D1: Hinweis (Vom Team erfragen)
A2: Geplante Absatzmenge | B2: 45000 | C2: Stück | D2: Planzahl Vertrieb
A3: Geplanter Preis | B3: 3000 | C3: EUR | D3: Planzahl Vertrieb
A4: --- KERNAUSGABEN ---
A5: Total Herstellkosten | B5: 90 | C5: MEUR | D5: inkl. Personal in Fertigung
A6: Total Verwaltungskosten | B6: 10 | C6: MEUR
A7: Total Marketing/Vertrieb | B7: 15 | C7: MEUR
A8: Forschung & Entwicklung (F&E) | B8: 2.5 | C8: MEUR | D8: Ökologie, Technologie, etc.
A9: Marktforschung | B9: 0.15 | C9: MEUR | D9: Kosten für Berichte / Analysen
A10: --- INVESTITIONEN ---
A11: Freiwillige Tilgung Langfristkr. | B11: 0 | C11: MEUR | D11: Cash-Out! Kurzfrist wird automatisch getilgt.
A12: Abschreibungen Alt-Anlagen | B12: 6 | C12: MEUR | D12: inklusive 0.25 MEUR fixe Gebäude-AfA
A13: Geplante Neuinvestition | B13: 15 | C13: MEUR | D13: Totaler Kaufpreis Anlage - Cash Out!
A14: Geplante Neu-Abschreibung | B14: 1.5 | C14: MEUR | D14: Z.B. 10% Lineare Abschreibung
A15: Veränderung Pensionsrückstellungen | B15: 2 | C15: MEUR | D15: Positiv = Cash-plus

Sheet 3_Szenario_Rechner
A1: Feld | B1: Szenario A (Defensiv) | C1: Szenario B (Aggressiv) | D1: Szenario C
A2: --- 1: EINGABEN (DEINE CFO ENTSCHEIDUNG) ---
A3: NEUER Kurzfristiger Kredit (MEUR) | B3: 15 | C3: 20 | D3: 10
A4: NEUER Langfristiger Kredit (MEUR) | B4: 0 | C4: 10 | D4: 0
A5: Dividende (MEUR) | B5: 1 | C5: 0 | D5: 2
A6: Geplanter Wertpapierkauf | B6: 0 | C6: 0 | D6: 0
A7: --- 2: BERECHNUNG EBIT & GEWINN ---
A8: Plan-Umsatz | B8: ='2_Team_Inputs'!B2*'2_Team_Inputs'!B3/1000000 | C8: ='2_Team_Inputs'!B2*'2_Team_Inputs'!B3/1000000 | D8: ='2_Team_Inputs'!B2*'2_Team_Inputs'!B3/1000000
A9: Plan-EBIT | B9: =B8-SUM('2_Team_Inputs'!B5:B9)-'2_Team_Inputs'!B12-'2_Team_Inputs'!B14 | C9: =C8-SUM('2_Team_Inputs'!B5:B9)-'2_Team_Inputs'!B12-'2_Team_Inputs'!B14 | D9: =D8-SUM('2_Team_Inputs'!B5:B9)-'2_Team_Inputs'!B12-'2_Team_Inputs'!B14
A10: Plan-Zinsaufwand | B10: =((B3+'1_Ist_Daten'!B7)*'1_Ist_Daten'!B11)+((B4+'1_Ist_Daten'!B8-'2_Team_Inputs'!B11)*'1_Ist_Daten'!B10) | C10: =((C3+'1_Ist_Daten'!B7)*'1_Ist_Daten'!B11)+((C4+'1_Ist_Daten'!B8-'2_Team_Inputs'!B11)*'1_Ist_Daten'!B10) | D10: =((D3+'1_Ist_Daten'!B7)*'1_Ist_Daten'!B11)+((D4+'1_Ist_Daten'!B8-'2_Team_Inputs'!B11)*'1_Ist_Daten'!B10)
A11: Plan-EBT (Ergebnis vor Steuern) | B11: =B9-B10 | C11: =C9-C10 | D11: =D9-D10
A12: Bemessungsgrundlage Steuer | B12: =MAX(0, B11-'1_Ist_Daten'!B5) | C12: =MAX(0, C11-'1_Ist_Daten'!B5) | D12: =MAX(0, D11-'1_Ist_Daten'!B5)
A13: Plan-Steuern | B13: =B12*'1_Ist_Daten'!B9 | C13: =C12*'1_Ist_Daten'!B9 | D13: =D12*'1_Ist_Daten'!B9
A14: Plan-Jahresüberschuss | B14: =B11-B13 | C14: =C11-C13 | D14: =D11-D13
A15: --- 3: TOPSIM ZIELEINGABEN ---
A16: Plan-Eigenkapital | B16: ='1_Ist_Daten'!B3+B14-B5 | C16: ='1_Ist_Daten'!B3+C14-C5 | D16: ='1_Ist_Daten'!B3+D14-D5
A17: Plan-EKR (%) | B17: =(B14/B16)*100 | C17: =(C14/C16)*100 | D17: =(D14/D16)*100
A18: Plan-Operativer Cashflow (MEUR) | B18: =B14+'2_Team_Inputs'!B12+'2_Team_Inputs'!B14+'2_Team_Inputs'!B15 | C18: =C14+'2_Team_Inputs'!B12+'2_Team_Inputs'!B14+'2_Team_Inputs'!B15 | D18: =D14+'2_Team_Inputs'!B12+'2_Team_Inputs'!B14+'2_Team_Inputs'!B15
A19: --- 4: TOPSIM FATAL CHECK ---
A20: Kassenbestand ENDE (Alarm < 0) | B20: ='1_Ist_Daten'!B2+B18+B3+B4-B5-'2_Team_Inputs'!B13-'1_Ist_Daten'!B7-'2_Team_Inputs'!B11-B6 | C20: ='1_Ist_Daten'!B2+C18+C3+C4-C5-'2_Team_Inputs'!B13-'1_Ist_Daten'!B7-'2_Team_Inputs'!B11-C6 | D20: ='1_Ist_Daten'!B2+D18+D3+D4-D5-'2_Team_Inputs'!B13-'1_Ist_Daten'!B7-'2_Team_Inputs'!B11-D6
